Siamese/__init__.py
Siamese/main.py
SimboloSiamese-0.2.8.dist-info/LICENSE.txt
SimboloSiamese-0.2.8.dist-info/METADATA
SimboloSiamese-0.2.8.dist-info/WHEEL
SimboloSiamese-0.2.8.dist-info/top_level.txt
SimboloSiamese-0.2.8.dist-info/RECORD
