Metadata-Version: 2.1
Name: SimboloSiamese
Version: 0.2.8
Author: Phyo Thu Htet, Min Thiha Htun, Ye Bhone Lin
License-File: LICENSE.txt
